universaldatatool/__init__.py
universaldatatool/camelify.py
universaldatatool/dataset.py
universaldatatool/interface.py
universaldatatool/load_csv.py
universaldatatool/load_json.py
universaldatatool/sample.py
universaldatatool/version.py
universaldatatool/nb/CollaborativeSession.py
universaldatatool/nb/ProxiedFileSession.py
universaldatatool/nb/PublicFileProxy.py
universaldatatool/nb/WebLocalFileProxyServer.py
universaldatatool/nb/__init__.py
universaldatatool/nb/edit_local.py
universaldatatool/nb/edit_online.py
universaldatatool/nb/open.py
universaldatatool/tests/__init__.py
universaldatatool/tests/example1.py
universaldatatool/tests/file_proxy.py
universaldatatool/tests/online_dataset.py
universaldatatool-0.0.4.dist-info/LICENSE
universaldatatool-0.0.4.dist-info/METADATA
universaldatatool-0.0.4.dist-info/WHEEL
universaldatatool-0.0.4.dist-info/top_level.txt
universaldatatool-0.0.4.dist-info/RECORD
