Metadata-Version: 2.1
Name: universaldatatool
Version: 0.0.4
Summary: Interact with any kind of kind of data directly in a jupyter notebook.
Home-page: https://github.com/UniversalDataTool/python-universaldatatool
Author: Severin Ibarluzea
Author-email: seve@universaldatatool.com
License: MIT
Platform: UNKNOWN
Classifier: Development Status :: 2 - Pre-Alpha
Classifier: Intended Audience :: Science/Research
Classifier: Programming Language :: Python :: 2.7
Classifier: Programming Language :: Python :: 3.6
